plotsense/__init__.py
plotsense/explanations/__init__.py
plotsense/explanations/explanations.py
plotsense/plot_generator/__init__.py
plotsense/plot_generator/generator.py
plotsense/visual_suggestion/__init__.py
plotsense/visual_suggestion/suggestions.py
plotsense-0.1.3.dist-info/licenses/LICENCE
plotsense-0.1.3.dist-info/licenses/NOTICE
test/__init__.py
test/test_explanations.py
test/test_plotgen.py
test/test_suggestions.py
plotsense-0.1.3.dist-info/METADATA
plotsense-0.1.3.dist-info/WHEEL
plotsense-0.1.3.dist-info/top_level.txt
plotsense-0.1.3.dist-info/RECORD
