Metadata-Version: 2.4
Name: plotsense
Version: 0.1.3
Summary: An intelligent plotting package with suggestions and explanations
Home-page: https://github.com/christianchimezie/PlotSenseAI
Author: Christian Chimezie, Toluwaleke Ogidan, Grace Farayola, Amaka Iduwe, Nelson Ogbeide, Onyekachukwu Ojumah, Olamilekan Ajao
Author-email: chimeziechristiancc@gmail.com, gbemilekeogidan@gmail.com, gracefarayola@gmail.com, nwaamaka_iduwe@yahoo.com, Ogbeide331@gmail.com, Onyekaojumah22@gmail.com, olamilekan011@gmail.com
License: Apache License 2.0
Project-URL: Documentation, https://github.com/christianchimezie/PlotSenseAI/blob/main/README.md
Classifier: Development Status :: 3 - Alpha
Classifier: Intended Audience :: Science/Research
Classifier: License :: OSI Approved :: MIT License
Classifier: Programming Language :: Python :: 3
Classifier: Programming Language :: Python :: 3.8
Classifier: Programming Language :: Python :: 3.9
Classifier: Programming Language :: Python :: 3.10
Classifier: Programming Language :: Python :: 3.11
Classifier: Programming Language :: Python :: 3.12
Classifier: Programming Language :: Python :: 3.13
Classifier: Topic :: Scientific/Engineering :: Visualization
Requires-Python: >=3.8
License-File: LICENCE
License-File: NOTICE
Requires-Dist: matplotlib>=3.8.0
Requires-Dist: seaborn>=0.11
Requires-Dist: pandas>=1.0
Requires-Dist: numpy>=1.18
Requires-Dist: python-dotenv
Requires-Dist: groq
Requires-Dist: requests
Dynamic: author
Dynamic: author-email
Dynamic: classifier
Dynamic: description
Dynamic: description-content-type
Dynamic: home-page
Dynamic: license
Dynamic: license-file
Dynamic: project-url
Dynamic: requires-dist
Dynamic: requires-python
Dynamic: summary
